[{"domain": "Expression of Ideas", "skill": "Transitions", "passage": "Martin Luther King Jr. was a key figure in the American civil rights movement, advocating for the end of racial segregation and equal rights for all. His nonviolent approach to activism was heavily influenced by Mahatma Gandhi's teachings. _______ Martin Luther King Jr. was awarded the Nobel Peace Prize in 1964 for his efforts in fighting racial inequality.", "question": "Which choice completes the text with the most logical transition?", "correct_answer": "C", "choices": {"A": "Alternatively,", "B": "On the other hand,", "C": "As a result,", "D": "In contrast,"}, "explanation": "C: 'As a result' is the correct answer because it logically connects the influence of Gandhi's teachings on King's nonviolent activism to the awarding of the Nobel Peace Prize.", "distractor_explanation": ["'On the other hand' is incorrect because it suggests a contrast with the previous sentence, which is not intended.", "'Alternatively' is incorrect because it implies an alternative to the previous sentence, which is not the case.", "'In contrast' is incorrect because it suggests a contrast with the previous sentence, which is not intended."], "id": 23571}]