[{"domain": "Craft and Structure", "skill": "Word In Context", "passage": "Ceramic engineering is a specialized field that focuses on creating advanced materials with unique properties. One of the key goals in this domain is to design ceramics that are both strong and ______, enabling them to withstand extreme conditions and perform optimally in various applications.", "question": "Which choice completes the text with the most logical and precise word or phrase?", "correct_answer": "A", "choices": {"A": "durable", "B": "versatile", "C": "fragile", "D": "common"}, "explanation": "A: 'durable' is the correct answer because it logically fits the context of designing ceramics that are strong and able to withstand extreme conditions.", "distractor_explanation": ["'versatile' is incorrect because it doesn't necessarily imply the ability to withstand extreme conditions.", "'fragile' is incorrect because it contradicts the goal of designing strong ceramics.", "'common' is incorrect because it doesn't convey the desired properties of the ceramics."], "id": 24219}]